advancedprinter/__init__.py
advancedprinter/main.py
AdvancedPrinter-1.2.0.dist-info/LICENSE
AdvancedPrinter-1.2.0.dist-info/METADATA
AdvancedPrinter-1.2.0.dist-info/WHEEL
AdvancedPrinter-1.2.0.dist-info/top_level.txt
AdvancedPrinter-1.2.0.dist-info/RECORD
