Metadata-Version: 2.1
Name: AdvancedPrinter
Version: 1.2.0
Summary: Used for printing to the CLI in different colors and styles
Home-page: https://github.com/kbkozlev/AdvancedPrinter
Author: Kaloian Kozlev
Author-email: kbkozlev@gmail.com
Project-URL: repository, https://github.com/kbkozlev/AdvancedPrinter
Classifier: Programming Language :: Python :: 3
Classifier: License :: OSI Approved :: MIT License
Classifier: Operating System :: OS Independent
Requires-Python: >=3.6
License-File: LICENSE
